{
	"name": "DF_CustomerPurchases",
	"properties": {
		"type": "MappingDataFlow",
		"typeProperties": {
			"sources": [
				{
					"dataset": {
						"referenceName": "DS_Storage_demobits_OLTP_PurchaseOrder",
						"type": "DatasetReference"
					},
					"name": "PurchaseOrder"
				},
				{
					"dataset": {
						"referenceName": "DS_Storage_demobits_OLTP_Customer",
						"type": "DatasetReference"
					},
					"name": "Customer"
				}
			],
			"sinks": [
				{
					"dataset": {
						"referenceName": "DS_SQL_demobitsdb_ProductPurchases2023",
						"type": "DatasetReference"
					},
					"name": "Output"
				}
			],
			"transformations": [
				{
					"name": "PurchaseOrderProjection"
				},
				{
					"name": "CustomerProjection"
				},
				{
					"name": "DataQualityCheck"
				},
				{
					"name": "JoinedStream"
				},
				{
					"name": "MetricCalculation"
				}
			],
			"scriptLines": [
				"source(output(",
				"          PurchaseOrderID as string,",
				"          { CustomerCode} as string,",
				"          ProductCode as string,",
				"          EmployeeCode as string,",
				"          { PuchaseOrderDate} as string,",
				"          { Quantity} as long,",
				"          { UnitPrice} as decimal(10,0)",
				"     ),",
				"     allowSchemaDrift: true,",
				"     validateSchema: false,",
				"     ignoreNoFilesFound: false) ~> PurchaseOrder",
				"source(output(",
				"          CustomerCode as string,",
				"          { CustomerName} as string,",
				"          { Address} as string,",
				"          { PhoneNumber} as integer",
				"     ),",
				"     allowSchemaDrift: true,",
				"     validateSchema: false,",
				"     ignoreNoFilesFound: false) ~> Customer",
				"PurchaseOrder select(mapColumn(",
				"          { CustomerCode},",
				"          { Quantity}",
				"     ),",
				"     skipDuplicateMapInputs: true,",
				"     skipDuplicateMapOutputs: true) ~> PurchaseOrderProjection",
				"Customer select(mapColumn(",
				"          CustomerCode,",
				"          { CustomerName}",
				"     ),",
				"     skipDuplicateMapInputs: true,",
				"     skipDuplicateMapOutputs: true) ~> CustomerProjection",
				"PurchaseOrderProjection filter(greater({ Quantity},0)) ~> DataQualityCheck",
				"DataQualityCheck, CustomerProjection join({ CustomerCode} == CustomerCode,",
				"     joinType:'inner',",
				"     matchType:'exact',",
				"     ignoreSpaces: false,",
				"     broadcast: 'auto')~> JoinedStream",
				"JoinedStream aggregate(groupBy({ CustomerCode},",
				"          { CustomerName}),",
				"     { ProductPurchases} = sum({ Quantity})) ~> MetricCalculation",
				"MetricCalculation sink(allowSchemaDrift: true,",
				"     validateSchema: false,",
				"     input(",
				"          CustomerCode as string,",
				"          CustomerName as string,",
				"          ProductPurchase as long",
				"     ),",
				"     deletable:false,",
				"     insertable:true,",
				"     updateable:false,",
				"     upsertable:false,",
				"     format: 'table',",
				"     skipDuplicateMapInputs: true,",
				"     skipDuplicateMapOutputs: true,",
				"     errorHandlingOption: 'stopOnFirstError',",
				"     mapColumn(",
				"          CustomerCode = { CustomerCode},",
				"          CustomerName = { CustomerName},",
				"          ProductPurchase = { ProductPurchases}",
				"     )) ~> Output"
			]
		}
	}
}